pydmr/__init__.py
pydmr/dmrfuncs.py
pydmr/pydict.py
pydmr/rw.py
pydmr-0.0.5.dist-info/licenses/LICENSE
pydmr-0.0.5.dist-info/METADATA
pydmr-0.0.5.dist-info/WHEEL
pydmr-0.0.5.dist-info/top_level.txt
pydmr-0.0.5.dist-info/RECORD
